<?xml version="1.0" encoding="us-ascii"?>
<terrain version="113">
    <heightMap tileSet="BelShir" uvtiling="24.000000 6.000000 0.000000 0.000000 " dim="257 65 " offset="0.000000 0.000000 0.000000 " scale="1.000000e+000 1.000000e+000 1.000000e+000 ">
        <cliffSetList num="1">
            <cliffSet i="0" name="BelShirCliff1"/>
        </cliffSetList>
        <rampList num="8">
            <ramp dir="2" hi="3" lo="2" leftLo="u(-1.000000e+000, 0.000000e+000) r(0.000000e+000, 1.000000e+000) c=(3.200000e+001, 9.000000e+000) w=1.000000e+000 h=2.000000e+000" leftHi="u(0.000000e+000, 0.000000e+000) r(0.000000e+000, 0.000000e+000) c=(0.000000e+000, 0.000000e+000) w=0.000000e+000 h=0.000000e+000" rightLo="u(-1.000000e+000, 0.000000e+000) r(0.000000e+000, 1.000000e+000) c=(3.200000e+001, 2.300000e+001) w=1.000000e+000 h=2.000000e+000" rightHi="u(0.000000e+000, 0.000000e+000) r(0.000000e+000, 0.000000e+000) c=(0.000000e+000, 0.000000e+000) w=0.000000e+000 h=0.000000e+000" base="u(-1.000000e+000, 0.000000e+000) r(0.000000e+000, 1.000000e+000) c=(3.100000e+001, 1.600000e+001) w=8.000000e+000 h=1.000000e+000" mid="u(-1.000000e+000, 0.000000e+000) r(0.000000e+000, 1.000000e+000) c=(3.200000e+001, 1.600000e+001) w=6.000000e+000 h=2.000000e+000" cid="0" leftLoVar="0" leftHiVar="4294967295" rightLoVar="0" rightHiVar="4294967295"/>
            <ramp dir="2" hi="2" lo="1" leftLo="u(-1.000000e+000, 0.000000e+000) r(0.000000e+000, 1.000000e+000) c=(6.400000e+001, 9.000000e+000) w=1.000000e+000 h=2.000000e+000" leftHi="u(0.000000e+000, 0.000000e+000) r(0.000000e+000, 0.000000e+000) c=(0.000000e+000, 0.000000e+000) w=0.000000e+000 h=0.000000e+000" rightLo="u(-1.000000e+000, 0.000000e+000) r(0.000000e+000, 1.000000e+000) c=(6.400000e+001, 2.300000e+001) w=1.000000e+000 h=2.000000e+000" rightHi="u(0.000000e+000, 0.000000e+000) r(0.000000e+000, 0.000000e+000) c=(0.000000e+000, 0.000000e+000) w=0.000000e+000 h=0.000000e+000" base="u(-1.000000e+000, 0.000000e+000) r(0.000000e+000, 1.000000e+000) c=(6.300000e+001, 1.600000e+001) w=8.000000e+000 h=1.000000e+000" mid="u(-1.000000e+000, 0.000000e+000) r(0.000000e+000, 1.000000e+000) c=(6.400000e+001, 1.600000e+001) w=6.000000e+000 h=2.000000e+000" cid="0" leftLoVar="0" leftHiVar="4294967295" rightLoVar="0" rightHiVar="4294967295"/>
            <ramp dir="3" hi="2" lo="1" leftLo="u(1.000000e+000, 0.000000e+000) r(0.000000e+000, -1.000000e+000) c=(1.920000e+002, 2.300000e+001) w=1.000000e+000 h=2.000000e+000" leftHi="u(0.000000e+000, 0.000000e+000) r(0.000000e+000, 0.000000e+000) c=(0.000000e+000, 0.000000e+000) w=0.000000e+000 h=0.000000e+000" rightLo="u(1.000000e+000, 0.000000e+000) r(0.000000e+000, -1.000000e+000) c=(1.920000e+002, 9.000000e+000) w=1.000000e+000 h=2.000000e+000" rightHi="u(0.000000e+000, 0.000000e+000) r(0.000000e+000, 0.000000e+000) c=(0.000000e+000, 0.000000e+000) w=0.000000e+000 h=0.000000e+000" base="u(1.000000e+000, 0.000000e+000) r(0.000000e+000, -1.000000e+000) c=(1.930000e+002, 1.600000e+001) w=8.000000e+000 h=1.000000e+000" mid="u(1.000000e+000, 0.000000e+000) r(0.000000e+000, -1.000000e+000) c=(1.920000e+002, 1.600000e+001) w=6.000000e+000 h=2.000000e+000" cid="0" leftLoVar="0" leftHiVar="4294967295" rightLoVar="0" rightHiVar="4294967295"/>
            <ramp dir="3" hi="3" lo="2" leftLo="u(1.000000e+000, 0.000000e+000) r(0.000000e+000, -1.000000e+000) c=(2.240000e+002, 2.300000e+001) w=1.000000e+000 h=2.000000e+000" leftHi="u(0.000000e+000, 0.000000e+000) r(0.000000e+000, 0.000000e+000) c=(0.000000e+000, 0.000000e+000) w=0.000000e+000 h=0.000000e+000" rightLo="u(1.000000e+000, 0.000000e+000) r(0.000000e+000, -1.000000e+000) c=(2.240000e+002, 9.000000e+000) w=1.000000e+000 h=2.000000e+000" rightHi="u(0.000000e+000, 0.000000e+000) r(0.000000e+000, 0.000000e+000) c=(0.000000e+000, 0.000000e+000) w=0.000000e+000 h=0.000000e+000" base="u(1.000000e+000, 0.000000e+000) r(0.000000e+000, -1.000000e+000) c=(2.250000e+002, 1.600000e+001) w=8.000000e+000 h=1.000000e+000" mid="u(1.000000e+000, 0.000000e+000) r(0.000000e+000, -1.000000e+000) c=(2.240000e+002, 1.600000e+001) w=6.000000e+000 h=2.000000e+000" cid="0" leftLoVar="0" leftHiVar="4294967295" rightLoVar="0" rightHiVar="4294967295"/>
            <ramp dir="2" hi="3" lo="2" leftLo="u(-1.000000e+000, 0.000000e+000) r(0.000000e+000, 1.000000e+000) c=(3.200000e+001, 4.100000e+001) w=1.000000e+000 h=2.000000e+000" leftHi="u(0.000000e+000, 0.000000e+000) r(0.000000e+000, 0.000000e+000) c=(0.000000e+000, 0.000000e+000) w=0.000000e+000 h=0.000000e+000" rightLo="u(-1.000000e+000, 0.000000e+000) r(0.000000e+000, 1.000000e+000) c=(3.200000e+001, 5.500000e+001) w=1.000000e+000 h=2.000000e+000" rightHi="u(0.000000e+000, 0.000000e+000) r(0.000000e+000, 0.000000e+000) c=(0.000000e+000, 0.000000e+000) w=0.000000e+000 h=0.000000e+000" base="u(-1.000000e+000, 0.000000e+000) r(0.000000e+000, 1.000000e+000) c=(3.100000e+001, 4.800000e+001) w=8.000000e+000 h=1.000000e+000" mid="u(-1.000000e+000, 0.000000e+000) r(0.000000e+000, 1.000000e+000) c=(3.200000e+001, 4.800000e+001) w=6.000000e+000 h=2.000000e+000" cid="0" leftLoVar="0" leftHiVar="4294967295" rightLoVar="0" rightHiVar="4294967295"/>
            <ramp dir="2" hi="2" lo="1" leftLo="u(-1.000000e+000, 0.000000e+000) r(0.000000e+000, 1.000000e+000) c=(6.400000e+001, 4.100000e+001) w=1.000000e+000 h=2.000000e+000" leftHi="u(0.000000e+000, 0.000000e+000) r(0.000000e+000, 0.000000e+000) c=(0.000000e+000, 0.000000e+000) w=0.000000e+000 h=0.000000e+000" rightLo="u(-1.000000e+000, 0.000000e+000) r(0.000000e+000, 1.000000e+000) c=(6.400000e+001, 5.500000e+001) w=1.000000e+000 h=2.000000e+000" rightHi="u(0.000000e+000, 0.000000e+000) r(0.000000e+000, 0.000000e+000) c=(0.000000e+000, 0.000000e+000) w=0.000000e+000 h=0.000000e+000" base="u(-1.000000e+000, 0.000000e+000) r(0.000000e+000, 1.000000e+000) c=(6.300000e+001, 4.800000e+001) w=8.000000e+000 h=1.000000e+000" mid="u(-1.000000e+000, 0.000000e+000) r(0.000000e+000, 1.000000e+000) c=(6.400000e+001, 4.800000e+001) w=6.000000e+000 h=2.000000e+000" cid="0" leftLoVar="0" leftHiVar="4294967295" rightLoVar="0" rightHiVar="4294967295"/>
            <ramp dir="3" hi="2" lo="1" leftLo="u(1.000000e+000, 0.000000e+000) r(0.000000e+000, -1.000000e+000) c=(1.920000e+002, 5.500000e+001) w=1.000000e+000 h=2.000000e+000" leftHi="u(0.000000e+000, 0.000000e+000) r(0.000000e+000, 0.000000e+000) c=(0.000000e+000, 0.000000e+000) w=0.000000e+000 h=0.000000e+000" rightLo="u(1.000000e+000, 0.000000e+000) r(0.000000e+000, -1.000000e+000) c=(1.920000e+002, 4.100000e+001) w=1.000000e+000 h=2.000000e+000" rightHi="u(0.000000e+000, 0.000000e+000) r(0.000000e+000, 0.000000e+000) c=(0.000000e+000, 0.000000e+000) w=0.000000e+000 h=0.000000e+000" base="u(1.000000e+000, 0.000000e+000) r(0.000000e+000, -1.000000e+000) c=(1.930000e+002, 4.800000e+001) w=8.000000e+000 h=1.000000e+000" mid="u(1.000000e+000, 0.000000e+000) r(0.000000e+000, -1.000000e+000) c=(1.920000e+002, 4.800000e+001) w=6.000000e+000 h=2.000000e+000" cid="0" leftLoVar="0" leftHiVar="4294967295" rightLoVar="0" rightHiVar="4294967295"/>
            <ramp dir="3" hi="3" lo="2" leftLo="u(1.000000e+000, 0.000000e+000) r(0.000000e+000, -1.000000e+000) c=(2.240000e+002, 5.500000e+001) w=1.000000e+000 h=2.000000e+000" leftHi="u(0.000000e+000, 0.000000e+000) r(0.000000e+000, 0.000000e+000) c=(0.000000e+000, 0.000000e+000) w=0.000000e+000 h=0.000000e+000" rightLo="u(1.000000e+000, 0.000000e+000) r(0.000000e+000, -1.000000e+000) c=(2.240000e+002, 4.100000e+001) w=1.000000e+000 h=2.000000e+000" rightHi="u(0.000000e+000, 0.000000e+000) r(0.000000e+000, 0.000000e+000) c=(0.000000e+000, 0.000000e+000) w=0.000000e+000 h=0.000000e+000" base="u(1.000000e+000, 0.000000e+000) r(0.000000e+000, -1.000000e+000) c=(2.250000e+002, 4.800000e+001) w=8.000000e+000 h=1.000000e+000" mid="u(1.000000e+000, 0.000000e+000) r(0.000000e+000, -1.000000e+000) c=(2.240000e+002, 4.800000e+001) w=6.000000e+000 h=2.000000e+000" cid="0" leftLoVar="0" leftHiVar="4294967295" rightLoVar="0" rightHiVar="4294967295"/>
        </rampList>
        <vertData quantizeBias="9.000965e+000" quantizeScale="2.746165e-004" standardHeight="8.000000e+000" name="t3HeightMap"/>
        <masks name="t3TextureMasks"/>
        <textureList num="8">
            <texture i="0" name="BelShirDirtLight"/>
            <texture i="1" name="BelShirDirtDark"/>
            <texture i="2" name="BelShirBricksLarge"/>
            <texture i="3" name="BelShirBrush"/>
            <texture i="4" name="BelShirGrassDark"/>
            <texture i="5" name="BelShirBricksSmall"/>
            <texture i="6" name="BelShirSmallTiles"/>
            <texture i="7" name="BelShirGrassLight"/>
        </textureList>
        <cliffCellList num="4096" numOccupied="448">
            <cc i="15" f="1" cid="0" cvar="3"/>
            <cc i="31" f="1" cid="0" cvar="2"/>
            <cc i="96" f="1" cid="0" cvar="2"/>
            <cc i="112" f="1" cid="0" cvar="3"/>
            <cc i="143" f="1" cid="0" cvar="3"/>
            <cc i="159" f="1" cid="0" cvar="2"/>
            <cc i="224" f="1" cid="0" cvar="2"/>
            <cc i="240" f="1" cid="0" cvar="3"/>
            <cc i="271" f="1" cid="0" cvar="0"/>
            <cc i="287" f="1" cid="0" cvar="1"/>
            <cc i="352" f="1" cid="0" cvar="0"/>
            <cc i="368" f="1" cid="0" cvar="3"/>
            <cc i="399" f="1" cid="0" cvar="0"/>
            <cc i="415" f="1" cid="0" cvar="0"/>
            <cc i="416" f="1" cid="0" cvar="2"/>
            <cc i="417" f="1" cid="0" cvar="1"/>
            <cc i="418" f="1" cid="0" cvar="0"/>
            <cc i="419" f="1" cid="0" cvar="2"/>
            <cc i="420" f="1" cid="0" cvar="1"/>
            <cc i="421" f="1" cid="0" cvar="1"/>
            <cc i="422" f="1" cid="0" cvar="0"/>
            <cc i="423" f="1" cid="0" cvar="0"/>
            <cc i="424" f="1" cid="0" cvar="3"/>
            <cc i="425" f="1" cid="0" cvar="2"/>
            <cc i="426" f="1" cid="0" cvar="0"/>
            <cc i="427" f="1" cid="0" cvar="2"/>
            <cc i="428" f="1" cid="0" cvar="2"/>
            <cc i="429" f="1" cid="0" cvar="3"/>
            <cc i="430" f="1" cid="0" cvar="3"/>
            <cc i="431" f="1" cid="0" cvar="1"/>
            <cc i="432" f="1" cid="0" cvar="0"/>
            <cc i="433" f="1" cid="0" cvar="0"/>
            <cc i="434" f="1" cid="0" cvar="1"/>
            <cc i="435" f="1" cid="0" cvar="1"/>
            <cc i="436" f="1" cid="0" cvar="3"/>
            <cc i="437" f="1" cid="0" cvar="0"/>
            <cc i="438" f="1" cid="0" cvar="2"/>
            <cc i="439" f="1" cid="0" cvar="1"/>
            <cc i="440" f="1" cid="0" cvar="2"/>
            <cc i="441" f="1" cid="0" cvar="2"/>
            <cc i="442" f="1" cid="0" cvar="2"/>
            <cc i="443" f="1" cid="0" cvar="1"/>
            <cc i="444" f="1" cid="0" cvar="0"/>
            <cc i="445" f="1" cid="0" cvar="1"/>
            <cc i="446" f="1" cid="0" cvar="1"/>
            <cc i="447" f="1" cid="0" cvar="3"/>
            <cc i="448" f="1" cid="0" cvar="0"/>
            <cc i="449" f="1" cid="0" cvar="2"/>
            <cc i="450" f="1" cid="0" cvar="0"/>
            <cc i="451" f="1" cid="0" cvar="0"/>
            <cc i="452" f="1" cid="0" cvar="3"/>
            <cc i="453" f="1" cid="0" cvar="3"/>
            <cc i="454" f="1" cid="0" cvar="0"/>
            <cc i="455" f="1" cid="0" cvar="0"/>
            <cc i="456" f="1" cid="0" cvar="3"/>
            <cc i="457" f="1" cid="0" cvar="3"/>
            <cc i="458" f="1" cid="0" cvar="1"/>
            <cc i="459" f="1" cid="0" cvar="1"/>
            <cc i="460" f="1" cid="0" cvar="1"/>
            <cc i="461" f="1" cid="0" cvar="3"/>
            <cc i="462" f="1" cid="0" cvar="0"/>
            <cc i="463" f="1" cid="0" cvar="0"/>
            <cc i="464" f="1" cid="0" cvar="0"/>
            <cc i="465" f="1" cid="0" cvar="1"/>
            <cc i="466" f="1" cid="0" cvar="2"/>
            <cc i="467" f="1" cid="0" cvar="2"/>
            <cc i="468" f="1" cid="0" cvar="0"/>
            <cc i="469" f="1" cid="0" cvar="1"/>
            <cc i="470" f="1" cid="0" cvar="3"/>
            <cc i="471" f="1" cid="0" cvar="2"/>
            <cc i="472" f="1" cid="0" cvar="3"/>
            <cc i="473" f="1" cid="0" cvar="0"/>
            <cc i="474" f="1" cid="0" cvar="0"/>
            <cc i="475" f="1" cid="0" cvar="0"/>
            <cc i="476" f="1" cid="0" cvar="1"/>
            <cc i="477" f="1" cid="0" cvar="1"/>
            <cc i="478" f="1" cid="0" cvar="3"/>
            <cc i="479" f="1" cid="0" cvar="0"/>
            <cc i="480" f="1" cid="0" cvar="0"/>
            <cc i="496" f="1" cid="0" cvar="0"/>
            <cc i="527" f="2" cid="0" cvar="1"/>
            <cc i="528" f="2" cid="0" cvar="2"/>
            <cc i="543" f="2" cid="0" cvar="1"/>
            <cc i="544" f="2" cid="0" cvar="0"/>
            <cc i="607" f="2" cid="0" cvar="2"/>
            <cc i="608" f="2" cid="0" cvar="1"/>
            <cc i="623" f="2" cid="0" cvar="2"/>
            <cc i="624" f="2" cid="0" cvar="2"/>
            <cc i="655" f="2" cid="0" cvar="1"/>
            <cc i="656" f="2" cid="0" cvar="3"/>
            <cc i="671" f="2" cid="0" cvar="1"/>
            <cc i="672" f="2" cid="0" cvar="0"/>
            <cc i="735" f="2" cid="0" cvar="0"/>
            <cc i="736" f="2" cid="0" cvar="0"/>
            <cc i="751" f="2" cid="0" cvar="0"/>
            <cc i="752" f="2" cid="0" cvar="0"/>
            <cc i="783" f="2" cid="0" cvar="0"/>
            <cc i="784" f="2" cid="0" cvar="1"/>
            <cc i="799" f="2" cid="0" cvar="0"/>
            <cc i="800" f="2" cid="0" cvar="3"/>
            <cc i="863" f="2" cid="0" cvar="0"/>
            <cc i="864" f="2" cid="0" cvar="3"/>
            <cc i="879" f="2" cid="0" cvar="2"/>
            <cc i="880" f="2" cid="0" cvar="3"/>
            <cc i="911" f="2" cid="0" cvar="2"/>
            <cc i="912" f="2" cid="0" cvar="0"/>
            <cc i="927" f="2" cid="0" cvar="0"/>
            <cc i="928" f="2" cid="0" cvar="0"/>
            <cc i="991" f="2" cid="0" cvar="1"/>
            <cc i="992" f="2" cid="0" cvar="0"/>
            <cc i="1007" f="2" cid="0" cvar="3"/>
            <cc i="1008" f="2" cid="0" cvar="2"/>
            <cc i="1039" f="2" cid="0" cvar="1"/>
            <cc i="1040" f="2" cid="0" cvar="3"/>
            <cc i="1055" f="2" cid="0" cvar="2"/>
            <cc i="1056" f="2" cid="0" cvar="2"/>
            <cc i="1119" f="2" cid="0" cvar="0"/>
            <cc i="1120" f="2" cid="0" cvar="2"/>
            <cc i="1135" f="2" cid="0" cvar="3"/>
            <cc i="1136" f="2" cid="0" cvar="3"/>
            <cc i="1167" f="2" cid="0" cvar="1"/>
            <cc i="1168" f="2" cid="0" cvar="2"/>
            <cc i="1183" f="2" cid="0" cvar="3"/>
            <cc i="1184" f="2" cid="0" cvar="2"/>
            <cc i="1247" f="2" cid="0" cvar="1"/>
            <cc i="1248" f="2" cid="0" cvar="3"/>
            <cc i="1263" f="2" cid="0" cvar="0"/>
            <cc i="1264" f="2" cid="0" cvar="3"/>
            <cc i="1295" f="2" cid="0" cvar="2"/>
            <cc i="1296" f="2" cid="0" cvar="3"/>
            <cc i="1311" f="2" cid="0" cvar="1"/>
            <cc i="1312" f="2" cid="0" cvar="1"/>
            <cc i="1375" f="2" cid="0" cvar="2"/>
            <cc i="1376" f="2" cid="0" cvar="2"/>
            <cc i="1391" f="2" cid="0" cvar="2"/>
            <cc i="1392" f="2" cid="0" cvar="3"/>
            <cc i="1423" f="2" cid="0" cvar="1"/>
            <cc i="1424" f="2" cid="0" cvar="3"/>
            <cc i="1439" f="2" cid="0" cvar="2"/>
            <cc i="1440" f="2" cid="0" cvar="1"/>
            <cc i="1503" f="2" cid="0" cvar="0"/>
            <cc i="1504" f="2" cid="0" cvar="2"/>
            <cc i="1519" f="2" cid="0" cvar="3"/>
            <cc i="1520" f="2" cid="0" cvar="3"/>
            <cc i="1551" f="1" cid="0" cvar="0"/>
            <cc i="1567" f="1" cid="0" cvar="0"/>
            <cc i="1568" f="1" cid="0" cvar="3"/>
            <cc i="1569" f="1" cid="0" cvar="2"/>
            <cc i="1570" f="1" cid="0" cvar="3"/>
            <cc i="1571" f="1" cid="0" cvar="3"/>
            <cc i="1572" f="1" cid="0" cvar="0"/>
            <cc i="1573" f="1" cid="0" cvar="0"/>
            <cc i="1574" f="1" cid="0" cvar="2"/>
            <cc i="1575" f="1" cid="0" cvar="2"/>
            <cc i="1576" f="1" cid="0" cvar="0"/>
            <cc i="1577" f="1" cid="0" cvar="0"/>
            <cc i="1578" f="1" cid="0" cvar="2"/>
            <cc i="1579" f="1" cid="0" cvar="0"/>
            <cc i="1580" f="1" cid="0" cvar="3"/>
            <cc i="1581" f="1" cid="0" cvar="1"/>
            <cc i="1582" f="1" cid="0" cvar="1"/>
            <cc i="1583" f="1" cid="0" cvar="0"/>
            <cc i="1584" f="1" cid="0" cvar="1"/>
            <cc i="1585" f="1" cid="0" cvar="2"/>
            <cc i="1586" f="1" cid="0" cvar="2"/>
            <cc i="1587" f="1" cid="0" cvar="2"/>
            <cc i="1588" f="1" cid="0" cvar="3"/>
            <cc i="1589" f="1" cid="0" cvar="1"/>
            <cc i="1590" f="1" cid="0" cvar="0"/>
            <cc i="1591" f="1" cid="0" cvar="2"/>
            <cc i="1592" f="1" cid="0" cvar="2"/>
            <cc i="1593" f="1" cid="0" cvar="1"/>
            <cc i="1594" f="1" cid="0" cvar="3"/>
            <cc i="1595" f="1" cid="0" cvar="1"/>
            <cc i="1596" f="1" cid="0" cvar="3"/>
            <cc i="1597" f="1" cid="0" cvar="1"/>
            <cc i="1598" f="1" cid="0" cvar="1"/>
            <cc i="1599" f="1" cid="0" cvar="0"/>
            <cc i="1600" f="1" cid="0" cvar="2"/>
            <cc i="1601" f="1" cid="0" cvar="0"/>
            <cc i="1602" f="1" cid="0" cvar="2"/>
            <cc i="1603" f="1" cid="0" cvar="0"/>
            <cc i="1604" f="1" cid="0" cvar="2"/>
            <cc i="1605" f="1" cid="0" cvar="0"/>
            <cc i="1606" f="1" cid="0" cvar="2"/>
            <cc i="1607" f="1" cid="0" cvar="1"/>
            <cc i="1608" f="1" cid="0" cvar="0"/>
            <cc i="1609" f="1" cid="0" cvar="0"/>
            <cc i="1610" f="1" cid="0" cvar="0"/>
            <cc i="1611" f="1" cid="0" cvar="0"/>
            <cc i="1612" f="1" cid="0" cvar="2"/>
            <cc i="1613" f="1" cid="0" cvar="3"/>
            <cc i="1614" f="1" cid="0" cvar="1"/>
            <cc i="1615" f="1" cid="0" cvar="0"/>
            <cc i="1616" f="1" cid="0" cvar="2"/>
            <cc i="1617" f="1" cid="0" cvar="3"/>
            <cc i="1618" f="1" cid="0" cvar="2"/>
            <cc i="1619" f="1" cid="0" cvar="2"/>
            <cc i="1620" f="1" cid="0" cvar="0"/>
            <cc i="1621" f="1" cid="0" cvar="0"/>
            <cc i="1622" f="1" cid="0" cvar="0"/>
            <cc i="1623" f="1" cid="0" cvar="0"/>
            <cc i="1624" f="1" cid="0" cvar="0"/>
            <cc i="1625" f="1" cid="0" cvar="0"/>
            <cc i="1626" f="1" cid="0" cvar="0"/>
            <cc i="1627" f="1" cid="0" cvar="0"/>
            <cc i="1628" f="1" cid="0" cvar="3"/>
            <cc i="1629" f="1" cid="0" cvar="3"/>
            <cc i="1630" f="1" cid="0" cvar="1"/>
            <cc i="1631" f="1" cid="0" cvar="0"/>
            <cc i="1632" f="1" cid="0" cvar="0"/>
            <cc i="1648" f="1" cid="0" cvar="3"/>
            <cc i="1679" f="1" cid="0" cvar="3"/>
            <cc i="1695" f="1" cid="0" cvar="0"/>
            <cc i="1760" f="1" cid="0" cvar="1"/>
            <cc i="1776" f="1" cid="0" cvar="0"/>
            <cc i="1807" f="1" cid="0" cvar="3"/>
            <cc i="1823" f="1" cid="0" cvar="2"/>
            <cc i="1888" f="1" cid="0" cvar="1"/>
            <cc i="1904" f="1" cid="0" cvar="0"/>
            <cc i="1935" f="1" cid="0" cvar="3"/>
            <cc i="1951" f="1" cid="0" cvar="2"/>
            <cc i="2016" f="1" cid="0" cvar="3"/>
            <cc i="2032" f="1" cid="0" cvar="3"/>
            <cc i="2063" f="1" cid="0" cvar="3"/>
            <cc i="2079" f="1" cid="0" cvar="0"/>
            <cc i="2144" f="1" cid="0" cvar="0"/>
            <cc i="2160" f="1" cid="0" cvar="3"/>
            <cc i="2191" f="1" cid="0" cvar="3"/>
            <cc i="2207" f="1" cid="0" cvar="1"/>
            <cc i="2272" f="1" cid="0" cvar="2"/>
            <cc i="2288" f="1" cid="0" cvar="3"/>
            <cc i="2319" f="1" cid="0" cvar="3"/>
            <cc i="2335" f="1" cid="0" cvar="0"/>
            <cc i="2400" f="1" cid="0" cvar="1"/>
            <cc i="2416" f="1" cid="0" cvar="0"/>
            <cc i="2447" f="1" cid="0" cvar="0"/>
            <cc i="2463" f="1" cid="0" cvar="0"/>
            <cc i="2464" f="1" cid="0" cvar="3"/>
            <cc i="2465" f="1" cid="0" cvar="2"/>
            <cc i="2466" f="1" cid="0" cvar="0"/>
            <cc i="2467" f="1" cid="0" cvar="0"/>
            <cc i="2468" f="1" cid="0" cvar="2"/>
            <cc i="2469" f="1" cid="0" cvar="3"/>
            <cc i="2470" f="1" cid="0" cvar="3"/>
            <cc i="2471" f="1" cid="0" cvar="1"/>
            <cc i="2472" f="1" cid="0" cvar="2"/>
            <cc i="2473" f="1" cid="0" cvar="2"/>
            <cc i="2474" f="1" cid="0" cvar="0"/>
            <cc i="2475" f="1" cid="0" cvar="1"/>
            <cc i="2476" f="1" cid="0" cvar="2"/>
            <cc i="2477" f="1" cid="0" cvar="3"/>
            <cc i="2478" f="1" cid="0" cvar="1"/>
            <cc i="2479" f="1" cid="0" cvar="3"/>
            <cc i="2480" f="1" cid="0" cvar="1"/>
            <cc i="2481" f="1" cid="0" cvar="0"/>
            <cc i="2482" f="1" cid="0" cvar="0"/>
            <cc i="2483" f="1" cid="0" cvar="3"/>
            <cc i="2484" f="1" cid="0" cvar="2"/>
            <cc i="2485" f="1" cid="0" cvar="1"/>
            <cc i="2486" f="1" cid="0" cvar="1"/>
            <cc i="2487" f="1" cid="0" cvar="1"/>
            <cc i="2488" f="1" cid="0" cvar="2"/>
            <cc i="2489" f="1" cid="0" cvar="3"/>
            <cc i="2490" f="1" cid="0" cvar="3"/>
            <cc i="2491" f="1" cid="0" cvar="3"/>
            <cc i="2492" f="1" cid="0" cvar="2"/>
            <cc i="2493" f="1" cid="0" cvar="3"/>
            <cc i="2494" f="1" cid="0" cvar="2"/>
            <cc i="2495" f="1" cid="0" cvar="3"/>
            <cc i="2496" f="1" cid="0" cvar="2"/>
            <cc i="2497" f="1" cid="0" cvar="1"/>
            <cc i="2498" f="1" cid="0" cvar="2"/>
            <cc i="2499" f="1" cid="0" cvar="1"/>
            <cc i="2500" f="1" cid="0" cvar="2"/>
            <cc i="2501" f="1" cid="0" cvar="3"/>
            <cc i="2502" f="1" cid="0" cvar="3"/>
            <cc i="2503" f="1" cid="0" cvar="2"/>
            <cc i="2504" f="1" cid="0" cvar="0"/>
            <cc i="2505" f="1" cid="0" cvar="2"/>
            <cc i="2506" f="1" cid="0" cvar="1"/>
            <cc i="2507" f="1" cid="0" cvar="2"/>
            <cc i="2508" f="1" cid="0" cvar="0"/>
            <cc i="2509" f="1" cid="0" cvar="1"/>
            <cc i="2510" f="1" cid="0" cvar="3"/>
            <cc i="2511" f="1" cid="0" cvar="0"/>
            <cc i="2512" f="1" cid="0" cvar="3"/>
            <cc i="2513" f="1" cid="0" cvar="3"/>
            <cc i="2514" f="1" cid="0" cvar="3"/>
            <cc i="2515" f="1" cid="0" cvar="0"/>
            <cc i="2516" f="1" cid="0" cvar="3"/>
            <cc i="2517" f="1" cid="0" cvar="3"/>
            <cc i="2518" f="1" cid="0" cvar="0"/>
            <cc i="2519" f="1" cid="0" cvar="3"/>
            <cc i="2520" f="1" cid="0" cvar="0"/>
            <cc i="2521" f="1" cid="0" cvar="1"/>
            <cc i="2522" f="1" cid="0" cvar="3"/>
            <cc i="2523" f="1" cid="0" cvar="2"/>
            <cc i="2524" f="1" cid="0" cvar="3"/>
            <cc i="2525" f="1" cid="0" cvar="2"/>
            <cc i="2526" f="1" cid="0" cvar="2"/>
            <cc i="2527" f="1" cid="0" cvar="1"/>
            <cc i="2528" f="1" cid="0" cvar="0"/>
            <cc i="2544" f="1" cid="0" cvar="3"/>
            <cc i="2575" f="2" cid="0" cvar="3"/>
            <cc i="2576" f="2" cid="0" cvar="3"/>
            <cc i="2591" f="2" cid="0" cvar="3"/>
            <cc i="2592" f="2" cid="0" cvar="3"/>
            <cc i="2655" f="2" cid="0" cvar="2"/>
            <cc i="2656" f="2" cid="0" cvar="3"/>
            <cc i="2671" f="2" cid="0" cvar="2"/>
            <cc i="2672" f="2" cid="0" cvar="1"/>
            <cc i="2703" f="2" cid="0" cvar="2"/>
            <cc i="2704" f="2" cid="0" cvar="1"/>
            <cc i="2719" f="2" cid="0" cvar="0"/>
            <cc i="2720" f="2" cid="0" cvar="0"/>
            <cc i="2783" f="2" cid="0" cvar="2"/>
            <cc i="2784" f="2" cid="0" cvar="1"/>
            <cc i="2799" f="2" cid="0" cvar="1"/>
            <cc i="2800" f="2" cid="0" cvar="3"/>
            <cc i="2831" f="2" cid="0" cvar="2"/>
            <cc i="2832" f="2" cid="0" cvar="3"/>
            <cc i="2847" f="2" cid="0" cvar="3"/>
            <cc i="2848" f="2" cid="0" cvar="3"/>
            <cc i="2911" f="2" cid="0" cvar="1"/>
            <cc i="2912" f="2" cid="0" cvar="1"/>
            <cc i="2927" f="2" cid="0" cvar="2"/>
            <cc i="2928" f="2" cid="0" cvar="1"/>
            <cc i="2959" f="2" cid="0" cvar="3"/>
            <cc i="2960" f="2" cid="0" cvar="0"/>
            <cc i="2975" f="2" cid="0" cvar="1"/>
            <cc i="2976" f="2" cid="0" cvar="2"/>
            <cc i="3039" f="2" cid="0" cvar="0"/>
            <cc i="3040" f="2" cid="0" cvar="0"/>
            <cc i="3055" f="2" cid="0" cvar="1"/>
            <cc i="3056" f="2" cid="0" cvar="2"/>
            <cc i="3087" f="2" cid="0" cvar="1"/>
            <cc i="3088" f="2" cid="0" cvar="0"/>
            <cc i="3103" f="2" cid="0" cvar="3"/>
            <cc i="3104" f="2" cid="0" cvar="0"/>
            <cc i="3167" f="2" cid="0" cvar="0"/>
            <cc i="3168" f="2" cid="0" cvar="2"/>
            <cc i="3183" f="2" cid="0" cvar="1"/>
            <cc i="3184" f="2" cid="0" cvar="1"/>
            <cc i="3215" f="2" cid="0" cvar="2"/>
            <cc i="3216" f="2" cid="0" cvar="2"/>
            <cc i="3231" f="2" cid="0" cvar="0"/>
            <cc i="3232" f="2" cid="0" cvar="1"/>
            <cc i="3295" f="2" cid="0" cvar="1"/>
            <cc i="3296" f="2" cid="0" cvar="2"/>
            <cc i="3311" f="2" cid="0" cvar="0"/>
            <cc i="3312" f="2" cid="0" cvar="2"/>
            <cc i="3343" f="2" cid="0" cvar="3"/>
            <cc i="3344" f="2" cid="0" cvar="3"/>
            <cc i="3359" f="2" cid="0" cvar="3"/>
            <cc i="3360" f="2" cid="0" cvar="1"/>
            <cc i="3423" f="2" cid="0" cvar="0"/>
            <cc i="3424" f="2" cid="0" cvar="2"/>
            <cc i="3439" f="2" cid="0" cvar="3"/>
            <cc i="3440" f="2" cid="0" cvar="0"/>
            <cc i="3471" f="2" cid="0" cvar="2"/>
            <cc i="3472" f="2" cid="0" cvar="3"/>
            <cc i="3487" f="2" cid="0" cvar="3"/>
            <cc i="3488" f="2" cid="0" cvar="2"/>
            <cc i="3551" f="2" cid="0" cvar="2"/>
            <cc i="3552" f="2" cid="0" cvar="3"/>
            <cc i="3567" f="2" cid="0" cvar="1"/>
            <cc i="3568" f="2" cid="0" cvar="0"/>
            <cc i="3599" f="1" cid="0" cvar="3"/>
            <cc i="3615" f="1" cid="0" cvar="0"/>
            <cc i="3616" f="1" cid="0" cvar="2"/>
            <cc i="3617" f="1" cid="0" cvar="3"/>
            <cc i="3618" f="1" cid="0" cvar="0"/>
            <cc i="3619" f="1" cid="0" cvar="3"/>
            <cc i="3620" f="1" cid="0" cvar="2"/>
            <cc i="3621" f="1" cid="0" cvar="0"/>
            <cc i="3622" f="1" cid="0" cvar="3"/>
            <cc i="3623" f="1" cid="0" cvar="2"/>
            <cc i="3624" f="1" cid="0" cvar="2"/>
            <cc i="3625" f="1" cid="0" cvar="2"/>
            <cc i="3626" f="1" cid="0" cvar="2"/>
            <cc i="3627" f="1" cid="0" cvar="2"/>
            <cc i="3628" f="1" cid="0" cvar="1"/>
            <cc i="3629" f="1" cid="0" cvar="1"/>
            <cc i="3630" f="1" cid="0" cvar="2"/>
            <cc i="3631" f="1" cid="0" cvar="2"/>
            <cc i="3632" f="1" cid="0" cvar="2"/>
            <cc i="3633" f="1" cid="0" cvar="0"/>
            <cc i="3634" f="1" cid="0" cvar="0"/>
            <cc i="3635" f="1" cid="0" cvar="2"/>
            <cc i="3636" f="1" cid="0" cvar="3"/>
            <cc i="3637" f="1" cid="0" cvar="2"/>
            <cc i="3638" f="1" cid="0" cvar="3"/>
            <cc i="3639" f="1" cid="0" cvar="3"/>
            <cc i="3640" f="1" cid="0" cvar="0"/>
            <cc i="3641" f="1" cid="0" cvar="1"/>
            <cc i="3642" f="1" cid="0" cvar="3"/>
            <cc i="3643" f="1" cid="0" cvar="0"/>
            <cc i="3644" f="1" cid="0" cvar="3"/>
            <cc i="3645" f="1" cid="0" cvar="1"/>
            <cc i="3646" f="1" cid="0" cvar="3"/>
            <cc i="3647" f="1" cid="0" cvar="1"/>
            <cc i="3648" f="1" cid="0" cvar="2"/>
            <cc i="3649" f="1" cid="0" cvar="3"/>
            <cc i="3650" f="1" cid="0" cvar="1"/>
            <cc i="3651" f="1" cid="0" cvar="2"/>
            <cc i="3652" f="1" cid="0" cvar="0"/>
            <cc i="3653" f="1" cid="0" cvar="1"/>
            <cc i="3654" f="1" cid="0" cvar="0"/>
            <cc i="3655" f="1" cid="0" cvar="2"/>
            <cc i="3656" f="1" cid="0" cvar="1"/>
            <cc i="3657" f="1" cid="0" cvar="1"/>
            <cc i="3658" f="1" cid="0" cvar="0"/>
            <cc i="3659" f="1" cid="0" cvar="1"/>
            <cc i="3660" f="1" cid="0" cvar="0"/>
            <cc i="3661" f="1" cid="0" cvar="0"/>
            <cc i="3662" f="1" cid="0" cvar="1"/>
            <cc i="3663" f="1" cid="0" cvar="2"/>
            <cc i="3664" f="1" cid="0" cvar="0"/>
            <cc i="3665" f="1" cid="0" cvar="1"/>
            <cc i="3666" f="1" cid="0" cvar="0"/>
            <cc i="3667" f="1" cid="0" cvar="2"/>
            <cc i="3668" f="1" cid="0" cvar="0"/>
            <cc i="3669" f="1" cid="0" cvar="3"/>
            <cc i="3670" f="1" cid="0" cvar="1"/>
            <cc i="3671" f="1" cid="0" cvar="2"/>
            <cc i="3672" f="1" cid="0" cvar="0"/>
            <cc i="3673" f="1" cid="0" cvar="3"/>
            <cc i="3674" f="1" cid="0" cvar="0"/>
            <cc i="3675" f="1" cid="0" cvar="3"/>
            <cc i="3676" f="1" cid="0" cvar="1"/>
            <cc i="3677" f="1" cid="0" cvar="2"/>
            <cc i="3678" f="1" cid="0" cvar="1"/>
            <cc i="3679" f="1" cid="0" cvar="3"/>
            <cc i="3680" f="1" cid="0" cvar="0"/>
            <cc i="3696" f="1" cid="0" cvar="3"/>
            <cc i="3727" f="1" cid="0" cvar="0"/>
            <cc i="3743" f="1" cid="0" cvar="1"/>
            <cc i="3808" f="1" cid="0" cvar="1"/>
            <cc i="3824" f="1" cid="0" cvar="3"/>
            <cc i="3855" f="1" cid="0" cvar="3"/>
            <cc i="3871" f="1" cid="0" cvar="3"/>
            <cc i="3936" f="1" cid="0" cvar="3"/>
            <cc i="3952" f="1" cid="0" cvar="3"/>
            <cc i="3983" f="1" cid="0" cvar="3"/>
            <cc i="3999" f="1" cid="0" cvar="2"/>
            <cc i="4064" f="1" cid="0" cvar="2"/>
            <cc i="4080" f="1" cid="0" cvar="3"/>
        </cliffCellList>
    </heightMap>
</terrain>
